gimme_db_token/__init__.py
gimme_db_token/__main__.py
gimme_db_token/_aws.py
gimme_db_token/_client.py
gimme_db_token/_config.py
gimme_db_token/_crypto.py
gimme_db_token/_pgpass.py
gimme_db_token/_token.py
cyral_gimme_db_token-0.8.4.dist-info/entry_points.txt
cyral_gimme_db_token-0.8.4.dist-info/WHEEL
cyral_gimme_db_token-0.8.4.dist-info/METADATA
cyral_gimme_db_token-0.8.4.dist-info/RECORD
